Paolog_Pynecraft/__init__.py
Paolog_Pynecraft/__main__.py
Paolog_Pynecraft/assets/help.txt
Paolog_Pynecraft/assets/rs/fonts/1001fonts-pixelon-eula.txt
Paolog_Pynecraft/assets/rs/fonts/Pixelon.otf
Paolog_Pynecraft/assets/rs/images/arm_texture.png
Paolog_Pynecraft/assets/rs/images/arm_texture.png.orig
Paolog_Pynecraft/assets/rs/images/basic_wood_block.png
Paolog_Pynecraft/assets/rs/images/basic_wood_planks_block.png
Paolog_Pynecraft/assets/rs/images/bedrock_block.png
Paolog_Pynecraft/assets/rs/images/brick_block.png
Paolog_Pynecraft/assets/rs/images/cursor.png
Paolog_Pynecraft/assets/rs/images/debug_block.png
Paolog_Pynecraft/assets/rs/images/dirt_block.png
Paolog_Pynecraft/assets/rs/images/dirt_block.png.old
Paolog_Pynecraft/assets/rs/images/error_debug_block.png
Paolog_Pynecraft/assets/rs/images/glass_block.png
Paolog_Pynecraft/assets/rs/images/grass_block.png
Paolog_Pynecraft/assets/rs/images/grass_block.png.old
Paolog_Pynecraft/assets/rs/images/old_basic_wood_block.png
Paolog_Pynecraft/assets/rs/images/paolog.png
Paolog_Pynecraft/assets/rs/images/pycr_logo.png
Paolog_Pynecraft/assets/rs/images/ra.png
Paolog_Pynecraft/assets/rs/images/ra2.png
Paolog_Pynecraft/assets/rs/images/skybox_day.png
Paolog_Pynecraft/assets/rs/images/skybox_night.png
Paolog_Pynecraft/assets/rs/images/slot.png
Paolog_Pynecraft/assets/rs/images/stone_block.png
Paolog_Pynecraft/assets/rs/images/water_block.png
Paolog_Pynecraft/assets/rs/objects/Grass_block.blend
Paolog_Pynecraft/assets/rs/objects/arm.blend
Paolog_Pynecraft/assets/rs/objects/arm.blend1
Paolog_Pynecraft/assets/rs/objects/arm.mtl
Paolog_Pynecraft/assets/rs/objects/arm.obj
Paolog_Pynecraft/assets/rs/objects/arm_texture.psd
Paolog_Pynecraft/assets/rs/objects/bed.mtl
Paolog_Pynecraft/assets/rs/objects/bed.obj
Paolog_Pynecraft/assets/rs/objects/bg_obj.mtl
Paolog_Pynecraft/assets/rs/objects/bg_obj.obj
Paolog_Pynecraft/assets/rs/objects/block.mtl
Paolog_Pynecraft/assets/rs/objects/block.obj
Paolog_Pynecraft-0.1.1.post2.dist-info/LICENSE.txt
Paolog_Pynecraft-0.1.1.post2.dist-info/METADATA
Paolog_Pynecraft-0.1.1.post2.dist-info/WHEEL
Paolog_Pynecraft-0.1.1.post2.dist-info/top_level.txt
Paolog_Pynecraft-0.1.1.post2.dist-info/RECORD
