Metadata-Version: 2.1
Name: Paolog_Pynecraft
Version: 0.1.1.post2
Summary: A Minecraft recreation made with Ursina
Author: Paolog
License-File: LICENSE.txt
Requires-Dist: ursina
Requires-Dist: appdata
Requires-Dist: perlin-noise
Requires-Dist: screeninfo
